deci_lab_client/__init__.py
deci_lab_client/api_client.py
deci_lab_client/configuration.py
deci_lab_client/exceptions.py
deci_lab_client/rest.py
deci_lab_client/api/__init__.py
deci_lab_client/api/platform_api.py
deci_lab_client/client/__init__.py
deci_lab_client/client/api_client.py
deci_lab_client/client/configuration.py
deci_lab_client/client/deci_platform_client.py
deci_lab_client/client/exceptions.py
deci_lab_client/client/helpers.py
deci_lab_client/models/__init__.py
deci_lab_client/models/accuracy_metric.py
deci_lab_client/models/accuracy_metric_key.py
deci_lab_client/models/accuracy_metric_type.py
deci_lab_client/models/accuracy_metrics_schema_response.py
deci_lab_client/models/activity_event_name.py
deci_lab_client/models/add_model_response.py
deci_lab_client/models/api_response.py
deci_lab_client/models/api_response_add_model_response.py
deci_lab_client/models/api_response_baseline_model_response_metadata.py
deci_lab_client/models/api_response_benchmark_request_metadata.py
deci_lab_client/models/api_response_bool.py
deci_lab_client/models/api_response_company_response_metadata.py
deci_lab_client/models/api_response_delete_model_response.py
deci_lab_client/models/api_response_dict_deci_common_data_types_enum_deep_learning_task_deep_learning_task_api_common_data_types_global_configuration_data_types_accuracy_metrics_schema_response.py
deci_lab_client/models/api_response_dict_deci_infra_data_types_enum_users_enums_activity_event_name_int.py
deci_lab_client/models/api_response_dict_str_any.py
deci_lab_client/models/api_response_gru_model_response.py
deci_lab_client/models/api_response_invite_in_db.py
deci_lab_client/models/api_response_list.py
deci_lab_client/models/api_response_list_deci_common_data_types_enum_model_frameworks_framework_type.py
deci_lab_client/models/api_response_list_deci_common_data_types_enum_models_enums_metric.py
deci_lab_client/models/api_response_list_deci_common_data_types_enum_models_enums_quantization_level.py
deci_lab_client-4.29.3.dist-info/METADATA
deci_lab_client-4.29.3.dist-info/WHEEL
deci_lab_client-4.29.3.dist-info/top_level.txt
deci_lab_client-4.29.3.dist-info/RECORD
