Metadata-Version: 2.1
Name: deci-lab-client
Version: 4.29.3
Summary: Deci Platform SDK
Home-page: UNKNOWN
Author: Deci AI
Author-email: rnd@deci.ai
License: UNKNOWN
Keywords: Deci,DeciAI,Platform
Platform: UNKNOWN
Requires-Dist: requests (==2.28.1)
Requires-Dist: six (==1.16.0)
Requires-Dist: cryptography (>=3.4.7)
Requires-Dist: python-dateutil (==2.8.2)
Requires-Dist: PyJWT (==2.4.0)
Requires-Dist: certifi
Requires-Dist: tqdm (~=4.64)
Requires-Dist: deci-common (>=12.0.0)
Requires-Dist: arrow (>=1.2.3)
